moneysuffixes/__init__.py
moneysuffixes/main.py
moneysuffixes-1.0.2.dist-info/METADATA
moneysuffixes-1.0.2.dist-info/WHEEL
moneysuffixes-1.0.2.dist-info/top_level.txt
moneysuffixes-1.0.2.dist-info/RECORD
