Metadata-Version: 2.1
Name: moneysuffixes
Version: 1.0.2
Summary: Shortens long amount of number.
Home-page: https://github.com/CantCode023/MoneySuffixes
Author: CantCode
Author-email: cantcode023@gmail.com
License: UNKNOWN
Platform: UNKNOWN
Classifier: Programming Language :: Python :: 3
Requires-Python: >=3.7
